coffee/__init__.py
coffee/free_data.py
coffee/ibvp.py
coffee/settings.py
coffee/system.py
coffee/actions/__init__.py
coffee/actions/actions.py
coffee/actions/hdf_output.py
coffee/actions/mpl_plotter.py
coffee/backend/__init__.py
coffee/backend/backend.py
coffee/diffop/__init__.py
coffee/diffop/fd.py
coffee/diffop/sbp/__init__.py
coffee/diffop/sbp/dissipation.py
coffee/diffop/sbp/dissipation_testing.nb
coffee/diffop/sbp/sbp.py
coffee/grid/__init__.py
coffee/grid/grid.py
coffee/io/__init__.py
coffee/io/simulation_data.py
coffee/mpi/__init__.py
coffee/mpi/mpiinterfaces.py
coffee/solvers/__init__.py
coffee/solvers/solvers.py
coffee/swsh/AxiSymmetric/__init__.py
coffee/swsh/AxiSymmetric/axial_spin_backward_transform.py
coffee/swsh/AxiSymmetric/axial_spin_forward_transform.py
coffee/swsh/AxiSymmetric/delta_matrices.py
coffee/swsh/AxiSymmetric/eths_operators.py
coffee/swsh/AxiSymmetric/example.py
coffee/swsh/AxiSymmetric/function_class.py
coffee/swsh/AxiSymmetric/precompute.py
coffee/swsh/AxiSymmetric/transforms.py
coffee/swsh/AxiSymmetric/weights.py
coffee/swsh/General/__init__.py
coffee/swsh/General/delta_matrices.py
coffee/swsh/General/eths.py
coffee/swsh/General/eths_operators.py
coffee/swsh/General/example.py
coffee/swsh/General/function_class.py
coffee/swsh/General/generator_of_swsh.py
coffee/swsh/General/precompute.py
coffee/swsh/General/spin_backward_transform.py
coffee/swsh/General/spin_forward_transform.py
coffee/swsh/General/transforms.py
coffee/swsh/General/weights.py
coffee/swsh/General/c_code/code/delta_matrices.c
coffee/swsh/General/c_code/code/eths.c
coffee/swsh/General/c_code/code/spin_backward_transform.c
coffee/swsh/General/c_code/code/spin_forward_transform.c
coffee/swsh/General/c_code/code/weights.c
coffee/tslices/__init__.py
coffee/tslices/tslices.py
coffeegrinder-0.3.4.dist-info/LICENSE.txt
coffeegrinder-0.3.4.dist-info/METADATA
coffeegrinder-0.3.4.dist-info/WHEEL
coffeegrinder-0.3.4.dist-info/top_level.txt
coffeegrinder-0.3.4.dist-info/RECORD
