Metadata-Version: 2.1
Name: coffeegrinder
Version: 0.3.4
Summary: COFFEE is an MPI-Parallelised Python package for the numerical evolution of time-dependent differential equations.
Home-page: https://github.com/coffee-gr/coffee
Author: Chris Stevens
Author-email: chris.stevens@canterbury.ac.nz
License: MIT
Project-URL: Documentation, https://pyscaffold.org/
Platform: any
Classifier: Development Status :: 4 - Beta
Classifier: Programming Language :: Python
License-File: LICENSE.txt
Requires-Dist: numpy
Requires-Dist: h5py
Requires-Dist: scipy
Requires-Dist: matplotlib
Requires-Dist: importlib-metadata ; python_version < "3.8"
Provides-Extra: jax
Requires-Dist: jax ; extra == 'jax'
Requires-Dist: jaxlib ; extra == 'jax'
Provides-Extra: mpi
Requires-Dist: mpi4py ; extra == 'mpi'
Provides-Extra: mpi-jax
Requires-Dist: mpi4py ; extra == 'mpi-jax'
Requires-Dist: jax ; extra == 'mpi-jax'
Requires-Dist: jaxlib ; extra == 'mpi-jax'
Provides-Extra: testing
Requires-Dist: setuptools ; extra == 'testing'
Requires-Dist: pytest ; extra == 'testing'
Requires-Dist: pytest-cov ; extra == 'testing'
